nonebot_plugin_r3nzskin/__init__.py
nonebot_plugin_r3nzskin/data_source.py
nonebot_plugin_r3nzskin/latest
nonebot_plugin_r3nzskin-0.1.2.dist-info/WHEEL
nonebot_plugin_r3nzskin-0.1.2.dist-info/METADATA
nonebot_plugin_r3nzskin-0.1.2.dist-info/RECORD
